__init__.py
directory_manager/__init__.py
directory_manager/directory.py
directory_manager-1.0.0.dist-info/licenses/LICENSE
utils/__init__.py
utils/u_debug.py
utils/u_funcs.py
utils/u_struct.py
directory_manager-1.0.0.dist-info/METADATA
directory_manager-1.0.0.dist-info/WHEEL
directory_manager-1.0.0.dist-info/entry_points.txt
directory_manager-1.0.0.dist-info/top_level.txt
directory_manager-1.0.0.dist-info/RECORD
