Metadata-Version: 2.4
Name: directory_manager
Version: 1.0.0
Summary: Creating prototypes, managing and visualizing directories.
Author-email: isme2121 <mohammedisme21@gmail.com>
Project-URL: Homepage, https://github.com/isme2121/directory_manager
Project-URL: Bug Tracker, https://github.com/isme2121/directory_manager/issues
Classifier: Programming Language :: Python :: 3
Classifier: License :: OSI Approved :: MIT License
Classifier: Operating System :: OS Independent
Requires-Python: >=3.12
License-File: LICENSE
Requires-Dist: prettytable==3.17.0
Requires-Dist: openpyxl==3.1.5
Requires-Dist: pillow==12.0.0
Requires-Dist: requests==2.32.5
Requires-Dist: pandas==2.3.3
Requires-Dist: colorama==0.4.6
Provides-Extra: test
Requires-Dist: pytest==9.0.1; extra == "test"
Dynamic: license-file
